osara/__init__.py
osara/db.py
osara/g.py
osara/tap.py
osara-0.0.3.dist-info/METADATA
osara-0.0.3.dist-info/WHEEL
osara-0.0.3.dist-info/top_level.txt
osara-0.0.3.dist-info/RECORD
