Metadata-Version: 2.1
Name: osara
Version: 0.0.3
Summary: micro-framewaork on top of kappa architecture
Home-page: http://github.com/hkwi/osara
Author: Hiroaki Kawai
Author-email: hiroaki.kawai@gmail.com
License: UNKNOWN
Platform: UNKNOWN
Classifier: Programming Language :: Python :: 3
Classifier: License :: OSI Approved :: MIT License
Classifier: Operating System :: OS Independent
Requires-Python: >=3.6
Requires-Dist: confluent-kafka
Requires-Dist: sqlalchemy
Requires-Dist: werkzeug
